inukit
